collection_frameworkvsss/__init__.py
collection_frameworkvsss/text.txt
collection_frameworkvsss/unique_characters.py
collection_frameworkvsss-0.0.6.dist-info/METADATA
collection_frameworkvsss-0.0.6.dist-info/WHEEL
collection_frameworkvsss-0.0.6.dist-info/licenses/LICENSE
collection_frameworkvsss-0.0.6.dist-info/RECORD
